dask_deltalake/__init__.py
dask_deltalake/__init__.pyi
dask_deltalake/core.py
dask_deltalake/core.pyi
dask_deltalake/writer.py
dask_deltalake-0.0.1.dist-info/WHEEL
dask_deltalake-0.0.1.dist-info/METADATA
dask_deltalake-0.0.1.dist-info/RECORD
