Metadata-Version: 2.1
Name: dask-deltalake
Version: 0.0.1
Summary: Dask + Deltalake
License: MIT
Author: Greg Hayes
Author-email: hayesgb@gmail.com
Requires-Python: >=3.8.1,<4
Classifier: License :: OSI Approved :: MIT License
Classifier: Programming Language :: Python :: 3
Classifier: Programming Language :: Python :: 3.9
Classifier: Programming Language :: Python :: 3.10
Classifier: Programming Language :: Python :: 3.11
Requires-Dist: bokeh (<3.0)
Requires-Dist: dask[dataframe] (>=2022.11.1,<2023.0.0)
Requires-Dist: deltalake (>=0.6.4,<0.7.0)
Requires-Dist: distributed (>=2022.11.1,<2023.0.0)
Requires-Dist: s3fs (>=2022.10.0)
